supers/__init__.py
supers/supers.py
supers-0.2.0.dist-info/LICENSE
supers-0.2.0.dist-info/METADATA
supers-0.2.0.dist-info/WHEEL
supers-0.2.0.dist-info/top_level.txt
supers-0.2.0.dist-info/RECORD
